scicamera/__init__.py
scicamera/actions.py
scicamera/camera.py
scicamera/configuration.py
scicamera/controls.py
scicamera/converters.py
scicamera/fake.py
scicamera/formats.py
scicamera/frame.py
scicamera/info.py
scicamera/lc_helpers.py
scicamera/request.py
scicamera/sensor_format.py
scicamera/testing.py
scicamera/timing.py
scicamera/tuning.py
scicamera/typing.py
scicamera-0.4.2.dist-info/LICENSE
scicamera-0.4.2.dist-info/METADATA
scicamera-0.4.2.dist-info/WHEEL
scicamera-0.4.2.dist-info/RECORD
