Metadata-Version: 2.1
Name: scicamera
Version: 0.4.2
Summary: 
Home-page: https://github.com/exclosure/scicamera
License: BSD
Keywords: camera,imaging,RaspberryPi
Author: Exclosure
Author-email: info@exclosure.io
Requires-Python: >=3.9,<4.0
Classifier: License :: Other/Proprietary License
Classifier: Programming Language :: Python :: 3
Classifier: Programming Language :: Python :: 3.9
Classifier: Programming Language :: Python :: 3.10
Classifier: Programming Language :: Python :: 3.11
Requires-Dist: numpy (>=1.23.5,<2.0.0)
Requires-Dist: pillow (>=9.3.0,<10.0.0)
Project-URL: Repository, https://github.com/exclosure/scicamera
